JynAi/__init__.py
JynAi/module.py
JynAi-4.dist-info/LICENSE
JynAi-4.dist-info/METADATA
JynAi-4.dist-info/WHEEL
JynAi-4.dist-info/top_level.txt
JynAi-4.dist-info/RECORD
