Metadata-Version: 2.1
Name: JynAi
Version: 4
Summary: JynAi Python Ai Module
Home-page: https://github.com/Jynoqtra/JynAi
Author: Jynoqtra
Author-email: Jynoqtra@gmail.com
Classifier: Programming Language :: Python :: 3
Classifier: License :: Other/Proprietary License
Classifier: Intended Audience :: Developers
License-File: LICENSE
Requires-Dist: requests
Requires-Dist: beautifulsoup4
Requires-Dist: transformers
Requires-Dist: torch
